.gitignore
LICENSE
MANIFEST.in
README.md
requirements.txt
setup.py
examples/sandbox.ipynb
examples/testing_casos.ipynb
src/polynomial_preprocessing/__init__.py
src/polynomial_preprocessing.egg-info/PKG-INFO
src/polynomial_preprocessing.egg-info/SOURCES.txt
src/polynomial_preprocessing.egg-info/dependency_links.txt
src/polynomial_preprocessing.egg-info/requires.txt
src/polynomial_preprocessing.egg-info/top_level.txt
src/polynomial_preprocessing/extrapolation_process/__init__.py
src/polynomial_preprocessing/extrapolation_process/gram_schmidt_extrapolation.py
src/polynomial_preprocessing/extrapolation_process/procesamiento_datos_continuos.py
src/polynomial_preprocessing/extrapolation_process/procesamiento_datos_grillados.py
src/polynomial_preprocessing/image_reconstruction/__init__.py
src/polynomial_preprocessing/image_reconstruction/conjugate_gradient.py
src/polynomial_preprocessing/image_reconstruction/conjugate_gradient_2.py
src/polynomial_preprocessing/optimization/__init__.py
src/polynomial_preprocessing/optimization/optimizacion_parametros_continuos.py
src/polynomial_preprocessing/optimization/optimizacion_parametros_grillados.py
src/polynomial_preprocessing/preprocessing/__init__.py
src/polynomial_preprocessing/preprocessing/preprocesamiento_datos_a_grillar.py
src/polynomial_preprocessing/preprocessing/preprocesamiento_datos_continuos.py