Metadata-Version: 2.1
Name: polynomial_preprocessing
Version: 1.0.4
Summary: Pre-procesamiento de alto rendimiento basado en polinomios discretos ortogonales para síntesis de imágenes
Home-page: https://github.com/StephanSilvaS/polynomial_preprocessing.git
Author: Stephan Silva Sanguinetti
Author-email: stephan.silva@usach.cl
Classifier: Programming Language :: Python :: 3.12
Classifier: License :: OSI Approved :: GNU General Public License v3 (GPLv3)
Classifier: Operating System :: POSIX :: Linux
Requires-Python: >=3.12
License-File: LICENSE
Requires-Dist: astropy==6.0.0
Requires-Dist: dask==2024.8.2
Requires-Dist: dafits==1.1.0
Requires-Dist: xarray==2024.01.1
Requires-Dist: zarr==2.18.2
Requires-Dist: dask-ms==0.2.21
Requires-Dist: distributed==2024.8.2
Requires-Dist: more-itertools==10.2.0
Requires-Dist: multimethod==1.11.2
Requires-Dist: numba==0.59.1
Requires-Dist: numpy<2.0.0
Requires-Dist: python-casacore==3.6.1
Requires-Dist: radio-beam==0.3.7
Requires-Dist: scipy==1.13.1
Requires-Dist: spectral-cube==0.6.5
Requires-Dist: cupy==13.2.0
Requires-Dist: optuna
Requires-Dist: line_profiler
